[
  {
    "id": 1,
    "first_name": "Dev",
    "last_name": "Account",
    "email": "dev.account@test.com",
    "answers": {
      "Dans quel unité es-tu ?": "Terminale",
      "Dans quelle classe es-tu ?": "Z",
      "Quel est ton style de musique préféré ?": "Pop",
      "Quel est pour toi le voyage idéal ?": "Voyage en couple",
      "Quelle est ta destination de rêve ?": "Marrakech",
      "Quel est ton genre de film/série préféré ?": "Drame",
      "Tu passes le plus de temps sur :": "Snapchat",
      "A l'école tu préfères :": "Sport",
      "Au petit-déjeuner c'est plutôt :": "Jus de fruit",
      "A Passy, le midi tu préfères être :": "Dans la cour",
      "Avec 1.000.000 d'euros tu ferais plutôt :": "L'achat d'une maison dans le Sud",
      "Comme super pouvoir, tu préfèrerais pouvoir :": "Lire dans les pensée",
      "Quelle est ta saison préférée :": "Hiver",
      "Tu préfères lire :": "Lire ?",
      "Tu préfères pratiquer quel sport :": "Sport collectif",
      "Quelle est ta soirée idéale ?": "Soirée cinéma",
      "Si tu pouvais dîner avec une personne historique ce serait :": "Jules César"
    }
  }
]